odoo/addons/stock_picking_info_lot/README.rst
odoo/addons/stock_picking_info_lot/__init__.py
odoo/addons/stock_picking_info_lot/__manifest__.py
odoo/addons/stock_picking_info_lot/i18n/es.po
odoo/addons/stock_picking_info_lot/i18n/it.po
odoo/addons/stock_picking_info_lot/i18n/stock_picking_info_lot.pot
odoo/addons/stock_picking_info_lot/models/__init__.py
odoo/addons/stock_picking_info_lot/models/product_template.py
odoo/addons/stock_picking_info_lot/models/stock_move_line.py
odoo/addons/stock_picking_info_lot/models/stock_picking.py
odoo/addons/stock_picking_info_lot/readme/CONFIGURE.rst
odoo/addons/stock_picking_info_lot/readme/CONTRIBUTORS.rst
odoo/addons/stock_picking_info_lot/readme/DESCRIPTION.rst
odoo/addons/stock_picking_info_lot/readme/ROADMAP.rst
odoo/addons/stock_picking_info_lot/readme/USAGE.rst
odoo/addons/stock_picking_info_lot/static/description/icon.png
odoo/addons/stock_picking_info_lot/static/description/index.html
odoo/addons/stock_picking_info_lot/tests/__init__.py
odoo/addons/stock_picking_info_lot/tests/test_picking_validation.py
odoo/addons/stock_picking_info_lot/views/product_template_views.xml
odoo/addons/stock_picking_info_lot/views/stock_move_line_views.xml
odoo_addon_stock_picking_info_lot-16.0.1.0.0.8.dist-info/METADATA
odoo_addon_stock_picking_info_lot-16.0.1.0.0.8.dist-info/WHEEL
odoo_addon_stock_picking_info_lot-16.0.1.0.0.8.dist-info/top_level.txt
odoo_addon_stock_picking_info_lot-16.0.1.0.0.8.dist-info/RECORD
